maleo/mixins/__init__.py
maleo/mixins/filter.py
maleo/mixins/general.py
maleo/mixins/hierarchy.py
maleo/mixins/identity.py
maleo/mixins/parameter.py
maleo/mixins/sort.py
maleo/mixins/status.py
maleo/mixins/timestamp.py
maleo_mixins-0.0.37.dist-info/licenses/LICENSE
maleo_mixins-0.0.37.dist-info/METADATA
maleo_mixins-0.0.37.dist-info/WHEEL
maleo_mixins-0.0.37.dist-info/top_level.txt
maleo_mixins-0.0.37.dist-info/RECORD
